setup.py
crash_hound/__init__.py
crash_hound.egg-info/PKG-INFO
crash_hound.egg-info/SOURCES.txt
crash_hound.egg-info/dependency_links.txt
crash_hound.egg-info/top_level.txt
test/test.py