Metadata-Version: 1.0
Name: crash-hound
Version: 2.1
Summary: Monitor anything and get notifications directly on your iPhone
Home-page: http://www.amix.dk/
Author: amix
Author-email: amix@amix.dk
License: BSD
Keywords: tropo crash hound notification sms crash reports monitoring
Platform: Any
Classifier: Development Status :: 5 - Production/Stable
Classifier: Intended Audience :: Developers
Classifier: License :: OSI Approved :: BSD License
Classifier: Operating System :: OS Independent
Classifier: Programming Language :: Python
Classifier: Topic :: Software Development :: Libraries :: Python Modules
